{
  "title": "Applicatieprofiel Verkeersborden",
  "category": "Applicatieprofiel",
  "usage": "TBD",
  "responsibleOrganisation": {
    "name": "Agentschap Wegen en Verkeer",
    "uri": "https://data.vlaanderen.be/id/organisatie/OVO000098"
  },
  "publicationDate": "TBD",
  "descriptionFileName": "ap-verkeersborden.md",
  "specificationDocuments": [
    {
      "name": "Applicatieprofiel Verkeersborden",
      "resourceReference": "https://data.vlaanderen.be/doc/applicatieprofiel/verkeersborden/"
    }
  ],
  "documentation": [],
  "charter": {},
  "reports": [
    {
      "name": "Verslag semantische werkgroep 1 - 22 augustus 2018",
      "resourceReference": "LBLOD_MOB_Verkeersborden_Workshop1_20180822_v20180822.docx.pdf"
    },
    {
      "name": "Verslag semantische werkgroep 2 - 21 september 2018",
      "resourceReference": "LBLOD_MOB_Verkeersborden_Workshop2_20180921_v20181004.docx.pdf"
    }
  ],
  "presentations": [
    {
      "name": "Presentatie semantische werkgroep 1 - 22 augustus 2018",
      "resourceReference": "LBLOD_WS1_Verkeersborden_20180823.pdf"
    },
    {
      "name": "Presentatie semantische werkgroep 2 - 21 september 2018",
      "resourceReference": "WS 2 verkeersborden.vlaanderen.pdf"
    },
    {
      "name": "Webinar - 23 november 2018",
      "resourceReference": "Verkeersborden_Semantisch_Model_v3.pdf"
    }
  ],
  "dateOfRegistration": "2018",
  "dateOfAcknowledgementByWorkingGroup": "TBD",
  "dateOfAcknowledgementBySteeringCommittee": "TBD"
}