{
  "title": {
    "nl": "Vocabularium Bestuur",
    "en": "Vocabulary Governance"
  },
  "category": {
    "nl": "https://data.vlaanderen.be/id/concept/StandaardType/Vocabularium",
    "en": "https://data.vlaanderen.be/id/concept/StandaardType/Vocabularium"
  },
  "usage": {
    "nl": "https://data.vlaanderen.be/id/concept/StandaardGebruik/Verplicht",
    "en": "https://data.vlaanderen.be/id/concept/StandaardGebruik/Verplicht"
  },
  "status": {
    "nl": "https://data.vlaanderen.be/id/concept/StandaardStatus/ErkendeStandaard",
    "en": "https://data.vlaanderen.be/id/concept/StandaardStatus/ErkendeStandaard"
  },
  "descriptionFileName": "voc-bestuur.md",
  "responsibleOrganisation": [
    {
      "name": {
        "nl": "Agentschap Binnenlands Bestuur",
        "en": "Agency for Domestic Administration"
      },
      "resourceReference": "http://data.vlaanderen.be/id/organisatie/OVO001835"
    }
  ],
  "publicationDate": "2018-06-26",
  "specificationDocuments": [
    {
      "name": {
        "nl": "Vocabularium Bestuur",
        "en": "Vocabulary Governance"
      },
      "resourceReference": "https://data.vlaanderen.be/ns/bestuur"
    }
  ],
  "documentation": [],
  "reports": [],
  "charter": {
    "resourceReference": "https://raw.githubusercontent.com/Informatievlaanderen/OSLOthema-lokaleBesluiten/standaardenregister/charter/"
  },
  "presentations": [],
  "dateOfRegistration": "2018-04-10 (retroactief)",
  "dateOfAcknowledgementByWorkingGroup": "2018-05-29",
  "dateOfAcknowledgementBySteeringCommittee": "2018-07-03",
  "repository": "OSLOthema-lokaleBesluiten",
  "datePublicReviewStart": "",
  "endOfPublicationDate": ""
}